{
  "kind": "collectionType",
  "collectionName": "client_sites",
  "info": {
    "singularName": "client-site",
    "pluralName": "client-sites",
    "displayName": "Client Site"
  },
  "options": {
    "draftAndPublish": true
  },
  "pluginOptions": {},
  "attributes": {
    "name": {
      "type": "string",
      "required": true
    },
    "thumbnail": {
      "type": "media",
      "multiple": false,
      "required": true,
      "allowedTypes": [
        "images",
        "files"
      ]
    },
    "url": {
      "type": "string",
      "required": true
    }
  }
}
